napari_nanopyx/__init__.py
napari_nanopyx/benchmarking.py
napari_nanopyx/channel_registration.py
napari_nanopyx/drift_alignment.py
napari_nanopyx/esrrf.py
napari_nanopyx/napari.yaml
napari_nanopyx/nlm_denoising.py
napari_nanopyx/squirrel.py
napari_nanopyx/srrf.py
napari_nanopyx/_tests/__init__.py
napari_nanopyx-0.2.4.dist-info/licenses/LICENSE
napari_nanopyx-0.2.4.dist-info/METADATA
napari_nanopyx-0.2.4.dist-info/WHEEL
napari_nanopyx-0.2.4.dist-info/entry_points.txt
napari_nanopyx-0.2.4.dist-info/top_level.txt
napari_nanopyx-0.2.4.dist-info/RECORD
