Metadata-Version: 2.4
Name: napari-nanopyx
Version: 0.2.4
Summary: napari plugin of Nanoscopy Python library (NanoPyx, the successor to NanoJ) - focused on light microscopy and super-resolution imaging
Author: Ricardo Henriques, Bruno Saraiva, Inês Cunha, António Brito
Author-email: bruno.msaraiva2@gmail.com
License: LGPL-3.0-only
Project-URL: Bug Tracker, https://github.com/HenriquesLab/napari-NanoPyx/issues
Project-URL: Documentation, https://github.com/HenriquesLab/napari-NanoPyx/wiki
Project-URL: Source Code, https://github.com/HenriquesLab/napari-NanoPyx
Project-URL: User Support, https://github.com/HenriquesLab/napari-NanoPyx/issues
Classifier: Development Status :: 2 - Pre-Alpha
Classifier: Framework :: napari
Classifier: Intended Audience :: Developers
Classifier: License :: OSI Approved :: GNU Lesser General Public License v3 (LGPLv3)
Classifier: Operating System :: OS Independent
Classifier: Programming Language :: Python
Classifier: Programming Language :: Python :: 3
Classifier: Topic :: Software Development :: Testing
Requires-Python: >=3.9
License-File: LICENSE
Requires-Dist: napari
Requires-Dist: nanopyx>=1.2
Requires-Dist: scikit-image
Requires-Dist: magicgui
Provides-Extra: testing
Requires-Dist: pytest; extra == "testing"
Requires-Dist: pytest-cov; extra == "testing"
Dynamic: license-file
